function_calling_tools/__init__.py
function_calling_tools/ntp.py
function_calling_tools/pirateweather.py
function_calling_tools/redmine.py
function_calling_tools-0.1.1.dist-info/LICENSE
function_calling_tools-0.1.1.dist-info/METADATA
function_calling_tools-0.1.1.dist-info/WHEEL
function_calling_tools-0.1.1.dist-info/RECORD
