Metadata-Version: 2.1
Name: function-calling-tools
Version: 0.1.1
Summary: 
Author: MarkInada
Author-email: makotoinada132@gmail.com
Requires-Python: >=3.8.1,<4.0.0
Classifier: Programming Language :: Python :: 3
Classifier: Programming Language :: Python :: 3.9
Classifier: Programming Language :: Python :: 3.10
Classifier: Programming Language :: Python :: 3.11
Requires-Dist: langchain (>=0.0.285,<0.0.286)
Requires-Dist: ntplib (>=0.4.0,<0.5.0)
